shml/__init__.py
shml/_version.py
shml/kinematics.py
shml/preprocessing.py
shml/preselection.py
shml/py.typed
shml/torch_dataset.py
shml/utils.py
shml/variables.py
shml/visualise.py
shml-0.1.dist-info/LICENSE
shml-0.1.dist-info/METADATA
shml-0.1.dist-info/WHEEL
shml-0.1.dist-info/top_level.txt
shml-0.1.dist-info/RECORD
