Metadata-Version: 2.1
Name: shml
Version: 0.1
Summary: lightweight pdata cleaning/processing/plotting/ML training library for use with an ATLAS BSM dihiggs search
Home-page: https://github.com/phinate/shml
Author: Nathan Simpson
Author-email: n.s@cern.ch
Maintainer: Nathan Simpson
Maintainer-email: n.s@cern.ch
License: BSD-3-Clause
Project-URL: Documentation, https://shml.readthedocs.io/
Project-URL: Bug Tracker, https://github.com/phinate/shml/issues
Project-URL: Discussions, https://github.com/phinate/shml/discussions
Project-URL: Changelog, https://github.com/phinate/shml/releases
Platform: Any
Classifier: Development Status :: 1 - Planning
Classifier: Intended Audience :: Developers
Classifier: Intended Audience :: Science/Research
Classifier: License :: OSI Approved :: BSD License
Classifier: Operating System :: OS Independent
Classifier: Programming Language :: Python
Classifier: Programming Language :: Python :: 3
Classifier: Programming Language :: Python :: 3 :: Only
Classifier: Programming Language :: Python :: 3.7
Classifier: Programming Language :: Python :: 3.8
Classifier: Programming Language :: Python :: 3.9
Classifier: Programming Language :: Python :: 3.10
Classifier: Topic :: Scientific/Engineering
Requires-Python: >=3.7
License-File: LICENSE
Requires-Dist: awkward (>=1.5.1)
Requires-Dist: pre-commit
Requires-Dist: pyarrow (>=6.0.0)
Requires-Dist: uproot (>=4.1.8)
Requires-Dist: typing-extensions (>=3.7) ; python_version < "3.8"
Provides-Extra: dev
Requires-Dist: pytest (>=6) ; extra == 'dev'
Provides-Extra: docs
Requires-Dist: Sphinx (~=3.0) ; extra == 'docs'
Requires-Dist: myst-parser (>=0.13) ; extra == 'docs'
Requires-Dist: sphinx-book-theme (>=0.1.0) ; extra == 'docs'
Requires-Dist: sphinx-copybutton ; extra == 'docs'
Provides-Extra: ml
Requires-Dist: jax ; extra == 'ml'
Requires-Dist: jaxlib ; extra == 'ml'
Requires-Dist: matplotlib ; extra == 'ml'
Requires-Dist: pytorch-lightning (>=1.5) ; extra == 'ml'
Provides-Extra: test
Requires-Dist: pytest (>=6) ; extra == 'test'
